{
  "AWSTemplateFormatVersion": "2010-09-09",
  "Description": "The AWS CloudFormation template for this Serverless application",
  "Resources": {
    "ServerlessDeploymentBucket": {
      "Type": "AWS::S3::Bucket",
      "Properties": {
        "BucketEncryption": {
          "ServerSideEncryptionConfiguration": [
            {
              "ServerSideEncryptionByDefault": {
                "SSEAlgorithm": "AES256"
              }
            }
          ]
        }
      }
    },
    "ServerlessDeploymentBucketPolicy": {
      "Type": "AWS::S3::BucketPolicy",
      "Properties": {
        "Bucket": {
          "Ref": "ServerlessDeploymentBucket"
        },
        "PolicyDocument": {
          "Statement": [
            {
              "Action": "s3:*",
              "Effect": "Deny",
              "Principal": "*",
              "Resource": [
                {
                  "Fn::Join": [
                    "",
                    [
                      "arn:",
                      {
                        "Ref": "AWS::Partition"
                      },
                      ":s3:::",
                      {
                        "Ref": "ServerlessDeploymentBucket"
                      },
                      "/*"
                    ]
                  ]
                },
                {
                  "Fn::Join": [
                    "",
                    [
                      "arn:",
                      {
                        "Ref": "AWS::Partition"
                      },
                      ":s3:::",
                      {
                        "Ref": "ServerlessDeploymentBucket"
                      }
                    ]
                  ]
                }
              ],
              "Condition": {
                "Bool": {
                  "aws:SecureTransport": false
                }
              }
            }
          ]
        }
      }
    },
    "ApiLogGroup": {
      "Type": "AWS::Logs::LogGroup",
      "Properties": {
        "LogGroupName": "/aws/lambda/rak-orion-backend-dev-api"
      }
    },
    "IamRoleLambdaExecution": {
      "Type": "AWS::IAM::Role",
      "Properties": {
        "AssumeRolePolicyDocument": {
          "Version": "2012-10-17",
          "Statement": [
            {
              "Effect": "Allow",
              "Principal": {
                "Service": [
                  "lambda.amazonaws.com"
                ]
              },
              "Action": [
                "sts:AssumeRole"
              ]
            }
          ]
        },
        "Policies": [
          {
            "PolicyName": {
              "Fn::Join": [
                "-",
                [
                  "rak-orion-backend",
                  "dev",
                  "lambda"
                ]
              ]
            },
            "PolicyDocument": {
              "Version": "2012-10-17",
              "Statement": [
                {
                  "Effect": "Allow",
                  "Action": [
                    "logs:CreateLogStream",
                    "logs:CreateLogGroup",
                    "logs:TagResource"
                  ],
                  "Resource": [
                    {
                      "Fn::Sub": "arn:${AWS::Partition}:logs:${AWS::Region}:${AWS::AccountId}:log-group:/aws/lambda/rak-orion-backend-dev*:*"
                    }
                  ]
                },
                {
                  "Effect": "Allow",
                  "Action": [
                    "logs:PutLogEvents"
                  ],
                  "Resource": [
                    {
                      "Fn::Sub": "arn:${AWS::Partition}:logs:${AWS::Region}:${AWS::AccountId}:log-group:/aws/lambda/rak-orion-backend-dev*:*:*"
                    }
                  ]
                }
              ]
            }
          }
        ],
        "Path": "/",
        "RoleName": {
          "Fn::Join": [
            "-",
            [
              "rak-orion-backend",
              "dev",
              {
                "Ref": "AWS::Region"
              },
              "lambdaRole"
            ]
          ]
        }
      }
    },
    "ApiLambdaFunction": {
      "Type": "AWS::Lambda::Function",
      "Properties": {
        "Code": {
          "S3Bucket": {
            "Ref": "ServerlessDeploymentBucket"
          },
          "S3Key": "serverless/rak-orion-backend/dev/1764879052013-2025-12-04T20:10:52.013Z/rak-orion-backend.zip"
        },
        "Handler": "src/index.handler",
        "Runtime": "nodejs18.x",
        "FunctionName": "rak-orion-backend-dev-api",
        "MemorySize": 512,
        "Timeout": 29,
        "Environment": {
          "Variables": {
            "NODE_ENV": "production",
            "DB_HOST": "rak-orion-db-instance-1.cczae2yi2rk2.us-east-1.rds.amazonaws.com",
            "DB_USER_PRODUCTION": "admin",
            "DB_PASSWORD_PRODUCTION": "1lS+e8&=OP1O",
            "DB_NAME_PRODUCTION": "rak_orion_db",
            "GEMINI_API_KEY": "AIzaSyAcVX21YgDN9pSAtuLFqCxwtilMiatMSi4",
            "EMAIL_USER": "horus@fabricadesoluciones.com",
            "EMAIL_PASS": "1-Mx8VR1hPQIRcTsqtBsvQ"
          }
        },
        "Role": {
          "Fn::GetAtt": [
            "IamRoleLambdaExecution",
            "Arn"
          ]
        }
      },
      "DependsOn": [
        "ApiLogGroup"
      ]
    },
    "ApiLambdaVersionprzPqqxks6LsBjbxXmg5iKX9HaF6SFCxny4nemQ": {
      "Type": "AWS::Lambda::Version",
      "DeletionPolicy": "Retain",
      "Properties": {
        "FunctionName": {
          "Ref": "ApiLambdaFunction"
        },
        "CodeSha256": "FoPvimgfbkqSg+vWIVgQETp4tty7L84SSu89NO5LVpM="
      }
    },
    "ApiGatewayRestApi": {
      "Type": "AWS::ApiGateway::RestApi",
      "Properties": {
        "Name": "dev-rak-orion-backend",
        "EndpointConfiguration": {
          "Types": [
            "EDGE"
          ]
        },
        "Policy": ""
      }
    },
    "ApiGatewayResourceProxyVar": {
      "Type": "AWS::ApiGateway::Resource",
      "Properties": {
        "ParentId": {
          "Fn::GetAtt": [
            "ApiGatewayRestApi",
            "RootResourceId"
          ]
        },
        "PathPart": "{proxy+}",
        "RestApiId": {
          "Ref": "ApiGatewayRestApi"
        }
      }
    },
    "ApiGatewayMethodOptions": {
      "Type": "AWS::ApiGateway::Method",
      "Properties": {
        "AuthorizationType": "NONE",
        "HttpMethod": "OPTIONS",
        "MethodResponses": [
          {
            "StatusCode": "200",
            "ResponseParameters": {
              "method.response.header.Access-Control-Allow-Origin": true,
              "method.response.header.Access-Control-Allow-Headers": true,
              "method.response.header.Access-Control-Allow-Methods": true
            },
            "ResponseModels": {}
          }
        ],
        "RequestParameters": {},
        "Integration": {
          "Type": "MOCK",
          "RequestTemplates": {
            "application/json": "{statusCode:200}"
          },
          "ContentHandling": "CONVERT_TO_TEXT",
          "IntegrationResponses": [
            {
              "StatusCode": "200",
              "ResponseParameters": {
                "method.response.header.Access-Control-Allow-Origin": "'*'",
                "method.response.header.Access-Control-Allow-Headers": "'Content-Type,X-Amz-Date,Authorization,X-Api-Key,X-Amz-Security-Token,X-Amz-User-Agent,X-Amzn-Trace-Id'",
                "method.response.header.Access-Control-Allow-Methods": "'OPTIONS,DELETE,GET,HEAD,PATCH,POST,PUT'"
              },
              "ResponseTemplates": {
                "application/json": ""
              }
            }
          ]
        },
        "ResourceId": {
          "Fn::GetAtt": [
            "ApiGatewayRestApi",
            "RootResourceId"
          ]
        },
        "RestApiId": {
          "Ref": "ApiGatewayRestApi"
        }
      }
    },
    "ApiGatewayMethodProxyVarOptions": {
      "Type": "AWS::ApiGateway::Method",
      "Properties": {
        "AuthorizationType": "NONE",
        "HttpMethod": "OPTIONS",
        "MethodResponses": [
          {
            "StatusCode": "200",
            "ResponseParameters": {
              "method.response.header.Access-Control-Allow-Origin": true,
              "method.response.header.Access-Control-Allow-Headers": true,
              "method.response.header.Access-Control-Allow-Methods": true
            },
            "ResponseModels": {}
          }
        ],
        "RequestParameters": {},
        "Integration": {
          "Type": "MOCK",
          "RequestTemplates": {
            "application/json": "{statusCode:200}"
          },
          "ContentHandling": "CONVERT_TO_TEXT",
          "IntegrationResponses": [
            {
              "StatusCode": "200",
              "ResponseParameters": {
                "method.response.header.Access-Control-Allow-Origin": "'*'",
                "method.response.header.Access-Control-Allow-Headers": "'Content-Type,X-Amz-Date,Authorization,X-Api-Key,X-Amz-Security-Token,X-Amz-User-Agent,X-Amzn-Trace-Id'",
                "method.response.header.Access-Control-Allow-Methods": "'OPTIONS,DELETE,GET,HEAD,PATCH,POST,PUT'"
              },
              "ResponseTemplates": {
                "application/json": ""
              }
            }
          ]
        },
        "ResourceId": {
          "Ref": "ApiGatewayResourceProxyVar"
        },
        "RestApiId": {
          "Ref": "ApiGatewayRestApi"
        }
      }
    },
    "ApiGatewayMethodAny": {
      "Type": "AWS::ApiGateway::Method",
      "Properties": {
        "HttpMethod": "ANY",
        "RequestParameters": {},
        "ResourceId": {
          "Fn::GetAtt": [
            "ApiGatewayRestApi",
            "RootResourceId"
          ]
        },
        "RestApiId": {
          "Ref": "ApiGatewayRestApi"
        },
        "ApiKeyRequired": false,
        "AuthorizationType": "NONE",
        "Integration": {
          "IntegrationHttpMethod": "POST",
          "Type": "AWS_PROXY",
          "Uri": {
            "Fn::Join": [
              "",
              [
                "arn:",
                {
                  "Ref": "AWS::Partition"
                },
                ":apigateway:",
                {
                  "Ref": "AWS::Region"
                },
                ":lambda:path/2015-03-31/functions/",
                {
                  "Fn::GetAtt": [
                    "ApiLambdaFunction",
                    "Arn"
                  ]
                },
                "/invocations"
              ]
            ]
          }
        },
        "MethodResponses": []
      },
      "DependsOn": [
        "ApiLambdaPermissionApiGateway"
      ]
    },
    "ApiGatewayMethodProxyVarAny": {
      "Type": "AWS::ApiGateway::Method",
      "Properties": {
        "HttpMethod": "ANY",
        "RequestParameters": {},
        "ResourceId": {
          "Ref": "ApiGatewayResourceProxyVar"
        },
        "RestApiId": {
          "Ref": "ApiGatewayRestApi"
        },
        "ApiKeyRequired": false,
        "AuthorizationType": "NONE",
        "Integration": {
          "IntegrationHttpMethod": "POST",
          "Type": "AWS_PROXY",
          "Uri": {
            "Fn::Join": [
              "",
              [
                "arn:",
                {
                  "Ref": "AWS::Partition"
                },
                ":apigateway:",
                {
                  "Ref": "AWS::Region"
                },
                ":lambda:path/2015-03-31/functions/",
                {
                  "Fn::GetAtt": [
                    "ApiLambdaFunction",
                    "Arn"
                  ]
                },
                "/invocations"
              ]
            ]
          }
        },
        "MethodResponses": []
      },
      "DependsOn": [
        "ApiLambdaPermissionApiGateway"
      ]
    },
    "ApiGatewayDeployment1764879045362": {
      "Type": "AWS::ApiGateway::Deployment",
      "Properties": {
        "RestApiId": {
          "Ref": "ApiGatewayRestApi"
        },
        "StageName": "dev"
      },
      "DependsOn": [
        "ApiGatewayMethodOptions",
        "ApiGatewayMethodProxyVarOptions",
        "ApiGatewayMethodAny",
        "ApiGatewayMethodProxyVarAny"
      ]
    },
    "ApiLambdaPermissionApiGateway": {
      "Type": "AWS::Lambda::Permission",
      "Properties": {
        "FunctionName": {
          "Fn::GetAtt": [
            "ApiLambdaFunction",
            "Arn"
          ]
        },
        "Action": "lambda:InvokeFunction",
        "Principal": "apigateway.amazonaws.com",
        "SourceArn": {
          "Fn::Join": [
            "",
            [
              "arn:",
              {
                "Ref": "AWS::Partition"
              },
              ":execute-api:",
              {
                "Ref": "AWS::Region"
              },
              ":",
              {
                "Ref": "AWS::AccountId"
              },
              ":",
              {
                "Ref": "ApiGatewayRestApi"
              },
              "/*/*"
            ]
          ]
        }
      }
    }
  },
  "Outputs": {
    "ServerlessDeploymentBucketName": {
      "Value": {
        "Ref": "ServerlessDeploymentBucket"
      },
      "Export": {
        "Name": "sls-rak-orion-backend-dev-ServerlessDeploymentBucketName"
      }
    },
    "ApiLambdaFunctionQualifiedArn": {
      "Description": "Current Lambda function version",
      "Value": {
        "Ref": "ApiLambdaVersionprzPqqxks6LsBjbxXmg5iKX9HaF6SFCxny4nemQ"
      },
      "Export": {
        "Name": "sls-rak-orion-backend-dev-ApiLambdaFunctionQualifiedArn"
      }
    },
    "ServiceEndpoint": {
      "Description": "URL of the service endpoint",
      "Value": {
        "Fn::Join": [
          "",
          [
            "https://",
            {
              "Ref": "ApiGatewayRestApi"
            },
            ".execute-api.",
            {
              "Ref": "AWS::Region"
            },
            ".",
            {
              "Ref": "AWS::URLSuffix"
            },
            "/dev"
          ]
        ]
      },
      "Export": {
        "Name": "sls-rak-orion-backend-dev-ServiceEndpoint"
      }
    }
  }
}